MANIFEST.in
requirements.txt
setup.py
test-requirements.txt
version.txt
cloudshell/__init__.py
cloudshell/networking/__init__.py
cloudshell/networking/sdn/__init__.py
cloudshell/networking/sdn/autoload/__init__.py
cloudshell/networking/sdn/autoload/sdn_generic_snmp_autoload.py
cloudshell/networking/sdn/configuration/__init__.py
cloudshell/networking/sdn/configuration/cloudshell_controller_binding_keys.py
cloudshell/networking/sdn/configuration/cloudshell_controller_bindings.py
cloudshell/networking/sdn/configuration/cloudshell_controller_configuration.py
cloudshell/networking/sdn/connectivity/__init__.py
cloudshell/networking/sdn/connectivity/apply_connectivity_operation.py
cloudshell/networking/sdn/controller/__init__.py
cloudshell/networking/sdn/controller/controller_connection_handler.py
cloudshell/networking/sdn/resolution/__init__.py
cloudshell/networking/sdn/resolution/topology_resolution.py
cloudshell/networking/sdn/static_flows/__init__.py
cloudshell/networking/sdn/static_flows/static_flows_configuration.py
cloudshell_sdn_core.egg-info/PKG-INFO
cloudshell_sdn_core.egg-info/SOURCES.txt
cloudshell_sdn_core.egg-info/dependency_links.txt
cloudshell_sdn_core.egg-info/requires.txt
cloudshell_sdn_core.egg-info/top_level.txt