Metadata-Version: 1.0
Name: cloudshell-sdn-core
Version: 1.0
Summary: QualiSystems Python package
Home-page: https://github.com/QualiSystems/cloudshell-sdn-core
Author: QualiSystems
Author-email: info@qualisystems.com
License: UNKNOWN
Platform: UNKNOWN
